vdx_helper/__init__.py
vdx_helper/domain.py
vdx_helper/errors.py
vdx_helper/mappers.py
vdx_helper/models.py
vdx_helper/py.typed
vdx_helper/util.py
vdx_helper/vdx_helper.py
vdx_helper-3.2.4.dist-info/LICENSE
vdx_helper-3.2.4.dist-info/METADATA
vdx_helper-3.2.4.dist-info/WHEEL
vdx_helper-3.2.4.dist-info/RECORD
