Metadata-Version: 2.1
Name: vdx-helper
Version: 3.2.4
Summary: Python client library to connect to the VDX Core API
Home-page: https://vizidox.com
License: MIT
Author: Joana Teixeira
Author-email: joana.teixeira@vizidox.com
Requires-Python: >=3.7,<4.0
Classifier: License :: OSI Approved :: MIT License
Classifier: Programming Language :: Python :: 3
Classifier: Programming Language :: Python :: 3.7
Classifier: Programming Language :: Python :: 3.8
Classifier: Programming Language :: Python :: 3.9
Classifier: Programming Language :: Python :: 3.10
Classifier: Programming Language :: Python :: 3.11
Classifier: Programming Language :: Python :: 3
Classifier: Topic :: Software Development :: Libraries :: Python Modules
Requires-Dist: nndict (>=2.0.1,<3.0.0)
Requires-Dist: requests (>=2.27,<3.0)
Project-URL: Documentation, https://helper.vizidox.com/
Project-URL: Repository, https://github.com/Morphotech/vdx-helper-python
